StarChecker/ChangeCheck.py
StarChecker/DevFind.py
StarChecker/__init__.py
starchecker-1.3.dist-info/licenses/LICENSE
starchecker-1.3.dist-info/METADATA
starchecker-1.3.dist-info/WHEEL
starchecker-1.3.dist-info/entry_points.txt
starchecker-1.3.dist-info/top_level.txt
starchecker-1.3.dist-info/RECORD
