Metadata-Version: 2.4
Name: StarChecker
Version: 1.3
Summary: A project that sends you SMS notifications via ntfy.sh when someone stars one of your devlogs!
Author-email: Shree Nag <shreeyuva2020@gmail.com>
License-Expression: MIT
Project-URL: homepage, https://github.com/shreeyuvan2020/devlog-star-checker
Project-URL: repository, https://github.com/shreeyuvan2020/devlog-star-checker/issues
Classifier: Programming Language :: Python :: 3
Classifier: Operating System :: OS Independent
Requires-Python: >=3.9
License-File: LICENSE
Requires-Dist: requests==2.32.4
Requires-Dist: selenium==4.33.0
Requires-Dist: beautifulsoup4==4.13.4
Requires-Dist: webdriver-manager==4.0.1
Dynamic: license-file
